{
  "_id": "65eee2e6143c9f64752ff4ed",
  "index": 2,
  "guid": "6d10a0d6-0f78-4aba-83c9-c4294db2b7d7",
  "is_active": true,
  "balance": "$2,311.60",
  "picture": "http://placehold.it/32x32",
  "city": "Coalmont",
  "zip_code": 9898,
  "state": "Missouri",
  "address": "931 Furman Avenue, Coalmont, Missouri, 9898",
  "age": 28,
  "eye_color": "green",
  "name": "Mamie Cline",
  "gender": "female",
  "company": "FORTEAN",
  "email": "mamiecline@fortean.com",
  "domain": "fortean.com",
  "phone": "+1 (902) 434-3004",
  "about": "Sit laborum aliquip nostrud enim ut. In aliqua qui proident magna nisi duis dolor excepteur. Voluptate anim enim enim nisi anim id aliquip nostrud amet excepteur duis cupidatat. Nostrud ad ut minim aliquip reprehenderit do duis occaecat incididunt cillum nisi. Do dolore ex proident consequat adipisicing ad dolore sint sunt.\r\n",
  "registered": "2023-11-30T06:24:48 -02:00",
  "latitude": -76.544559,
  "longitude": 133.724694,
  "tags": [
    "exercitation",
    "quis",
    "laboris",
    "est",
    "Lorem",
    "commodo",
    "eu"
  ],
  "friends": [
    {
      "id": 0,
      "name": "Serena Whitaker"
    },
    {
      "id": 1,
      "name": "Alexandria Gill"
    },
    {
      "id": 2,
      "name": "Simon Hanson"
    },
    {
      "id": 3,
      "name": "Briana Gallagher"
    }
  ],
  "greeting": "Hello, Mamie Cline! You have 8 unread messages.",
  "favorite_fruit": "banana",
  "department": "",
  "salary": 0,
  "experience_year": 0
}